prompt_protector/__init__.py
prompt_protector/chat_gpt.py
prompt_protector/input_auditor.py
prompt_protector/output_auditor.py
prompt_protector/prompt_protector.py
prompt_protector/settings.py
prompt_protector-0.1.dist-info/METADATA
prompt_protector-0.1.dist-info/WHEEL
prompt_protector-0.1.dist-info/top_level.txt
prompt_protector-0.1.dist-info/RECORD
